Workbook

Sheet Calculadora
A1: Calculadora básica: cuánto pedir sabiendo IRPF, IVA y costes fijos
A2: Edita las celdas azules. El IRPF queda fijo al 15% como pediste. Los costes son una cantidad fija en euros.
A4: Entradas | D4: Resumen para enseñarle al socio
A5: Neto que quiere ganarse | B5: 21000 | C5: € | D5: Debe pedir de base | E5: =B18 -> 24950 | F5: sin IVA
A6: Costes fijos del trabajo | B6: 200 | C6: € | D6: IVA que se añade | E6: =B24 -> 5239.5 | F6: no es ganancia
A7: IRPF fijo | B7: 0.15 | C7: % | D7: Factura total | E7: =B25 -> 30189.5 | F7: base + IVA
A8: IVA | B8: 0.21 | C8: % | D8: Cliente paga | E8: =B26 -> 26447 | F8: si hay retención
A9: Retención aplicada en factura | B9: Sí | D9: Se queda neto | E9: =B22 -> 21007.5 | F9: después de IRPF y costes
A10: Redondear base hacia arriba a | B10: 50 | C10: €
A12: Modelo usado: Base antes de IVA - IRPF 15% - costes fijos = neto final. La fórmula sube la base para que el neto final llegue al objetivo.
A14: Resultados principales | D14: Desglose de lo que se va
A15: Lo que quiere ganarse neto | B15: =B5 -> 21000 | D15: Concepto | E15: Importe | F15: % base
A16: Lo que quiere ganarse antes de IRPF (sin costes) | B16: =B5/(1-B7) -> 24705.882 | D16: Neto final | E16: =B22 -> 21007.5 | F16: =E16/$B$18 -> 0.84198397
A17: IRPF sobre esa ganancia (sin costes) | B17: =B16*B7 -> 3705.8824 | D17: IRPF 15% | E17: =B19 -> 3742.5 | F17: =E17/$B$18 -> 0.15
A18: Base recomendada a pedir antes de IVA | B18: =IF(B10>0,ROUNDUP(((B5+B6)/(1-B7))/B10,0)*B10,(B5+B6)/(1-B7)) -> 24950 | D18: Costes fijos | E18: =B20 -> 200 | F18: =E18/$B$18 -> 0.0080160321
A19: IRPF 15% retenido/apartado sobre la base | B19: =B18*B7 -> 3742.5 | D19: Base total | E19: =SUM(E16:E18) -> 24950 | F19: =E19/$B$18 -> 1
A20: Costes fijos que se van | B20: =B6 -> 200 | D20: IVA añadido aparte | E20: =B24 -> 5239.5 | F20: =E20/$B$18 -> 0.21
A21: Ganancia antes de IRPF real, después de costes | B21: =B18-B20 -> 24750
A22: Neto final estimado | B22: =B18-B19-B20 -> 21007.5
A23: Diferencia vs neto deseado | B23: =B22-B5 -> 7.5
A24: IVA a cobrar / ingresar | B24: =B18*B8 -> 5239.5
A25: Total factura antes de retención | B25: =B18+B24 -> 30189.5
A26: Total que paga cliente | B26: =IF(B9="Sí",B25-B19,B25) -> 26447
A27: Total impuestos + costes | B27: =B19+B20+B24 -> 9182
A28: Dinero a apartar del cobro recibido | B28: =IF(B9="Sí",B24+B20,B24+B19+B20) -> 5439.5
A29: % de la base que se va en IRPF + costes | B29: =(B19+B20)/B18 -> 0.15801603
A31: Cómo explicarlo en 30 segundos
A32: 1 | B32: Primero pones el neto que quiere quedarse y sus costes fijos reales.
A33: 2 | B33: Como el IRPF es 15%, el Excel calcula cuánto tiene que haber antes de IRPF.
A34: 3 | B34: Después suma los costes y calcula la base que hay que pedir para que, tras IRPF y costes, quede el neto objetivo.
A35: 4 | B35: El IVA se muestra aparte porque normalmente se cobra al cliente pero no es beneficio.

Sheet Escenarios
A1: Escenarios con costes fijos e IRPF fijo del 15%
A2: Cambia solo las columnas azules. El resto calcula cuánto pedir y cuánto se va en IRPF, costes e IVA.
A4: Escenario | B4: Neto deseado (€) | C4: Costes fijos (€) | D4: IVA | E4: IRPF fijo | F4: Redondeo (€) | G4: Retención aplicada | H4: Base a pedir (€) | I4: IRPF 15% (€) | J4: Costes (€) | K4: IVA (€) | L4: Total factura (€) | M4: Total paga cliente (€) | N4: Neto final (€)
A5: Actual calculadora | B5: =Calculadora!B5 -> 21000 | C5: =Calculadora!B6 -> 200 | D5: =Calculadora!B8 -> 0.21 | E5: 0.15 | F5: =Calculadora!B10 -> 50 | G5: =Calculadora!B9 -> Sí | H5: =IF(F5>0,ROUNDUP(((B5+C5)/(1-E5))/F5,0)*F5,(B5+C5)/(1-E5)) -> 24950 | I5: =H5*E5 -> 3742.5 | J5: =C5 -> 200 | K5: =H5*D5 -> 5239.5 | L5: =H5+K5 -> 30189.5 | M5: =IF(G5="Sí",L5-I5,L5) -> 26447 | N5: =H5-I5-J5 -> 21007.5
A6: Sin costes | B6: 2500 | C6: 0 | D6: 0.21 | E6: 0.15 | F6: 50 | G6: Sí | H6: =IF(F6>0,ROUNDUP(((B6+C6)/(1-E6))/F6,0)*F6,(B6+C6)/(1-E6)) -> 2950 | I6: =H6*E6 -> 442.5 | J6: =C6 -> 0 | K6: =H6*D6 -> 619.5 | L6: =H6+K6 -> 3569.5 | M6: =IF(G6="Sí",L6-I6,L6) -> 3127 | N6: =H6-I6-J6 -> 2507.5
A7: Costes bajos | B7: 2500 | C7: 250 | D7: 0.21 | E7: 0.15 | F7: 50 | G7: Sí | H7: =IF(F7>0,ROUNDUP(((B7+C7)/(1-E7))/F7,0)*F7,(B7+C7)/(1-E7)) -> 3250 | I7: =H7*E7 -> 487.5 | J7: =C7 -> 250 | K7: =H7*D7 -> 682.5 | L7: =H7+K7 -> 3932.5 | M7: =IF(G7="Sí",L7-I7,L7) -> 3445 | N7: =H7-I7-J7 -> 2512.5
A8: Costes medios | B8: 2500 | C8: 500 | D8: 0.21 | E8: 0.15 | F8: 50 | G8: Sí | H8: =IF(F8>0,ROUNDUP(((B8+C8)/(1-E8))/F8,0)*F8,(B8+C8)/(1-E8)) -> 3550 | I8: =H8*E8 -> 532.5 | J8: =C8 -> 500 | K8: =H8*D8 -> 745.5 | L8: =H8+K8 -> 4295.5 | M8: =IF(G8="Sí",L8-I8,L8) -> 3763 | N8: =H8-I8-J8 -> 2517.5
A9: Costes altos | B9: 2500 | C9: 1000 | D9: 0.21 | E9: 0.15 | F9: 50 | G9: Sí | H9: =IF(F9>0,ROUNDUP(((B9+C9)/(1-E9))/F9,0)*F9,(B9+C9)/(1-E9)) -> 4150 | I9: =H9*E9 -> 622.5 | J9: =C9 -> 1000 | K9: =H9*D9 -> 871.5 | L9: =H9+K9 -> 5021.5 | M9: =IF(G9="Sí",L9-I9,L9) -> 4399 | N9: =H9-I9-J9 -> 2527.5
A10: Sin retención en factura | B10: 2500 | C10: 500 | D10: 0.21 | E10: 0.15 | F10: 50 | G10: No | H10: =IF(F10>0,ROUNDUP(((B10+C10)/(1-E10))/F10,0)*F10,(B10+C10)/(1-E10)) -> 3550 | I10: =H10*E10 -> 532.5 | J10: =C10 -> 500 | K10: =H10*D10 -> 745.5 | L10: =H10+K10 -> 4295.5 | M10: =IF(G10="Sí",L10-I10,L10) -> 4295.5 | N10: =H10-I10-J10 -> 2517.5

Sheet Guía y fuentes
A1: Guía rápida y fuentes
A3: Qué cambiar | B3: Dónde | C3: Qué significa | D3: Consejo
A4: Neto que quiere ganarse | B4: Calculadora!B5 | C4: Cantidad final que desea conservar. | D4: Separadlo de la facturación: facturar más no siempre significa ganar más.
A5: Costes fijos | B5: Calculadora!B6 | C5: Cantidad fija que se va en entregar el trabajo. | D5: Incluid importes reales: subcontratas, materiales, licencias, herramientas o desplazamientos.
A6: IRPF fijo | B6: Calculadora!B7 | C6: Premisa fija del 15%. | D6: Está marcado en amarillo porque normalmente no se toca en esta versión.
A7: IVA | B7: Calculadora!B8 | C7: IVA que se suma a la factura. | D7: No lo tratéis como beneficio propio.
A8: Redondeo | B8: Calculadora!B10 | C8: Redondea la base a un múltiplo comercial. | D8: Poned 0 si queréis el cálculo exacto sin redondear.
A10: Fórmula / concepto | B10: Cálculo | C10: Qué muestra | D10: Observación
A11: Lo que quiere ganarse antes de IRPF | B11: Neto deseado / (1 - 15%) | C11: La ganancia bruta necesaria para que, descontando IRPF, quede el neto deseado. | D11: Se muestra en Calculadora!B16.
A12: Base a pedir antes de IVA | B12: (Neto deseado + costes fijos) / (1 - 15%) | C12: La base recomendada para que, tras IRPF y costes, quede el neto objetivo. | D12: Se redondea si Calculadora!B10 es mayor que 0.
A13: IRPF | B13: Base a pedir × 15% | C13: La parte que se retiene o se aparta. | D13: En factura profesional suele calcularse sobre la base antes de IVA.
A14: Neto final | B14: Base a pedir - IRPF - costes fijos | C14: La comprobación de cuánto queda limpio. | D14: Debe coincidir o superar el neto deseado si hay redondeo.
A15: IVA | B15: Base a pedir × IVA | C15: Lo que se añade al cliente. | D15: Se cobra, pero no se considera ganancia neta.
... A19: Retención profesional general | B19: 15% fijo en este archivo | C19: Agencia Tributaria — Otras obligaciones fiscales. Retenciones | D19: https://sede.agenciatributaria.gob.es/Sede/ayuda/manuales-videos-folletos/manuales-practicos/folleto-actividades-economicas/7-otras-obligaciones-fiscales-retenciones.html
A21: Aviso: este archivo es una calculadora sencilla para conversación y planificación. Los impuestos reales dependen del caso, país, actividad, régimen fiscal, gastos deducibles y forma jurídica; conviene validarlo con un asesor.
